Workbook

Sheet Assumptions
A1: VoiceLink Pricing Model v3.2
A3: Anthropic API Pricing (USD, March 2026)
A4: Model | B4: Input $/MTok | C4: Output $/MTok | D4: Role in VoiceLink
A5: Claude Haiku 4.5 | B5: 1 | C5: 5 | D5: Main model — transcription, routing, CRM actions
A6: Claude Sonnet 4.5 | B6: 3 | C6: 15 | D6: Response generation (small outputs per message)
A8: Key Inputs
A9: Haiku input price ($/MTok) | B9: 1 | D9: Same as Haiku 4.5 — main cost driver
A10: Sonnet output price ($/MTok) | B10: 15 | D10: For response generation
A11: Avg output tokens per message | B11: 670 | D11: Observed from test data (94:1 ratio)
A12: USD → EUR exchange rate | B12: 0.92 | D12: Conservative estimate
A13: Infrastructure per user/mo (€) | B13: 2 | D13: Supabase, Stripe, hosting, monitoring
A14: 1 credit = X tokens | B14: 10000 | D14: Display unit for users
A16: Derived Costs
A17: Haiku cost in EUR (€/MTok) | B17: =B9*B12 -> 0.92 | D17: Haiku $ × EUR rate
A18: Sonnet output cost per msg (€) | B18: =B10*B11/1000000*B12 -> 0.009246 | D18: Sonnet output $/MTok × avg tokens × EUR rate
A19: Avg input tokens per message | B19: 63098 | D19: Observed average from test data
A20: Cost per avg message (€) | B20: =B17*B19/1000000+B18 -> 0.06729616 | D20: Haiku input cost + Sonnet output overhead
A21: Cost per 100 credits (€) | B21: =B17*B14*100/1000000 -> 0.92 | D21: Haiku EUR rate × 1M tokens
A22: Messages per 100 credits (approx) | B22: =B14*100/B19 -> 15.848363 | D22: Based on avg tokens per message

Sheet Tier Overview
A1: Plan Structure
B3: Free Trial | C3: Starter | D3: Professional | E3: Business
A4: Monthly price | B4: Free | C4: €24 | D4: €59 | E4: €109
A5: Credits / user | B5: 100 | C5: 350 | D5: 1,000 | E5: 2,000
A6: Token allowance | B6: 1M | C6: 3.5M | D6: 10M | E6: 20M
A7: ≈ Voice notes | B7: ~10–14 | C7: ~35–50 | D7: ~100–142 | E7: ~200–285
A8: Billing type | B8: One-time | C8: Monthly | D8: Monthly | E8: Monthly
A9: Auto top-up | B9: ✗ | C9: ✗ | D9: ✓ @ €7/100cr | E9: ✓ @ €7/100cr
A10: Volume discounts | B10: ✗ | C10: ✗ | D10: Up to 18% | E10: Up to 15%
A11: Support | B11: — | C11: Email | D11: Priority | E11: Dedicated AM
A13: Upgrade Value Story
A14: Starter → Professional | B14: 2.9× credits for 2.5× price = 1.2× better value
A15: Professional → Business | B15: 2.0× credits for 1.8× price = 1.1× better value

Sheet Margin Analysis
A1: Margin Analysis — Per User Per Month
A2: Haiku $1/MTok + Sonnet output overhead + €2 infra
A4: Tier | B4: Revenue € | C4: Haiku Cost € | D4: Sonnet OH € | E4: Infra € | F4: Total Cost € | G4: Margin € | H4: Margin %
A5: Free Trial | B5: 0 | C5: =1*Assumptions!B17 -> 0.92 | D5: =12*Assumptions!B18 -> 0.110952 | E5: 0 | F5: =C5+D5+E5 -> 1.030952 | G5: 0 | H5: 0
A6: Starter | B6: 24 | C6: =3.5*Assumptions!B17 -> 3.22 | D6: =42*Assumptions!B18 -> 0.388332 | E6: =Assumptions!B13 -> 2 | F6: =C6+D6+E6 -> 5.608332 | G6: =B6-F6 -> 18.391668 | H6: =G6/B6 -> 0.7663195
A7: Professional | B7: 59 | C7: =10*Assumptions!B17 -> 9.2 | D7: =120*Assumptions!B18 -> 1.10952 | E7: =Assumptions!B13 -> 2 | F7: =C7+D7+E7 -> 12.30952 | G7: =B7-F7 -> 46.69048 | H7: =G7/B7 -> 0.79136407
A8: Business | B8: 109 | C8: =20*Assumptions!B17 -> 18.4 | D8: =240*Assumptions!B18 -> 2.21904 | E8: =Assumptions!B13 -> 2 | F8: =C8+D8+E8 -> 22.61904 | G8: =B8-F8 -> 86.38096 | H8: =G8/B8 -> 0.79248587
A10: Auto Top-Up
A11: Config | B11: Revenue € | C11: Haiku Cost € | D11: Sonnet OH € | E11: Infra € | F11: Total Cost € | G11: Margin € | H11: Margin %
A12: Auto top-up (100cr) | B12: 7 | C12: =1*Assumptions!B17 -> 0.92 | D12: =Assumptions!B22*Assumptions!B18 -> 0.14653396 | E12: 0 | F12: =C12+D12+E12 -> 1.066534 | G12: =B12-F12 -> 5.933466 | H12: =G12/B12 -> 0.84763801

Sheet Volume Discounts
A1: Volume Discount Margins
A3: Professional — €59 base, 1,000 credits
A4: Users | B4: Discount | C4: Price/User € | D4: Haiku Cost € | E4: Total Cost € | F4: Margin € | G4: Margin %
A5: 1–3 | B5: 0 | C5: =59*(1-B5) -> 59 | D5: =10*Assumptions!B17 -> 9.2 | E5: =D5+120*Assumptions!B18+Assumptions!B13 -> 12.30952 | F5: =C5-E5 -> 46.69048 | G5: =F5/C5 -> 0.79136407
A6: 4–6 | B6: 0.05 | C6: =59*(1-B6) -> 56.05 | D6: =10*Assumptions!B17 -> 9.2 | E6: =D6+120*Assumptions!B18+Assumptions!B13 -> 12.30952 | F6: =C6-E6 -> 43.74048 | G6: =F6/C6 -> 0.78038323
A7: 7–10 | B7: 0.08 | C7: =59*(1-B7) -> 54.28 | D7: =10*Assumptions!B17 -> 9.2 | E7: =D7+120*Assumptions!B18+Assumptions!B13 -> 12.30952 | F7: =C7-E7 -> 41.97048 | G7: =F7/C7 -> 0.77322181
A8: 11–15 | B8: 0.12 | C8: =59*(1-B8) -> 51.92 | D8: =10*Assumptions!B17 -> 9.2 | E8: =D8+120*Assumptions!B18+Assumptions!B13 -> 12.30952 | F8: =C8-E8 -> 39.61048 | G8: =F8/C8 -> 0.76291371
A9: 16–25 | B9: 0.15 | C9: =59*(1-B9) -> 50.15 | D9: =10*Assumptions!B17 -> 9.2 | E9: =D9+120*Assumptions!B18+Assumptions!B13 -> 12.30952 | F9: =C9-E9 -> 37.84048 | G9: =F9/C9 -> 0.75454596
A10: 26–50 | B10: 0.18 | C10: =59*(1-B10) -> 48.38 | D10: =10*Assumptions!B17 -> 9.2 | E10: =D10+120*Assumptions!B18+Assumptions!B13 -> 12.30952 | F10: =C10-E10 -> 36.07048 | G10: =F10/C10 -> 0.74556594
A13: Business — €109 base, 2,000 credits
A14: Users | B14: Discount | C14: Price/User € | D14: Haiku Cost € | E14: Total Cost € | F14: Margin € | G14: Margin %
A15: 1–3 | B15: 0 | C15: =109*(1-B15) -> 109 | D15: =20*Assumptions!B17 -> 18.4 | E15: =D15+240*Assumptions!B18+Assumptions!B13 -> 22.61904 | F15: =C15-E15 -> 86.38096 | G15: =F15/C15 -> 0.79248587
A16: 4–6 | B16: 0.05 | C16: =109*(1-B16) -> 103.55 | D16: =20*Assumptions!B17 -> 18.4 | E16: =D16+240*Assumptions!B18+Assumptions!B13 -> 22.61904 | F16: =C16-E16 -> 80.93096 | G16: =F16/C16 -> 0.78156408
A17: 7–10 | B17: 0.08 | C17: =109*(1-B17) -> 100.28 | D17: =20*Assumptions!B17 -> 18.4 | E17: =D17+240*Assumptions!B18+Assumptions!B13 -> 22.61904 | F17: =C17-E17 -> 77.66096 | G17: =F17/C17 -> 0.77444116
A18: 11–15 | B18: 0.12 | C18: =109*(1-B18) -> 95.92 | D18: =20*Assumptions!B17 -> 18.4 | E18: =D18+240*Assumptions!B18+Assumptions!B13 -> 22.61904 | F18: =C18-E18 -> 73.30096 | G18: =F18/C18 -> 0.76418849
A19: 16–25 | B19: 0.15 | C19: =109*(1-B19) -> 92.65 | D19: =20*Assumptions!B17 -> 18.4 | E19: =D19+240*Assumptions!B18+Assumptions!B13 -> 22.61904 | F19: =C19-E19 -> 70.03096 | G19: =F19/C19 -> 0.75586573

Sheet Scenarios
A1: Team Revenue Scenarios — Professional Plan
A2: Change Assumptions sheet inputs (blue) to model different costs
A4: Metric | B4: 10 users (8% disc) | C4: 25 users (15% disc) | D4: 50 users (18% disc)
A5: Price per user (€/mo) | B5: =59*(1-0.08) -> 54.28 | C5: =59*(1-0.15) -> 50.15 | D5: =59*(1-0.18) -> 48.38
A6: Monthly team revenue (€) | B6: =B5*10 -> 542.8 | C6: =C5*25 -> 1253.75 | D6: =D5*50 -> 2419
A7: Cost per user (€/mo) | B7: =10*Assumptions!B17+120*Assumptions!B18+Assumptions!B13 -> 12.30952 | C7: =10*Assumptions!B17+120*Assumptions!B18+Assumptions!B13 -> 12.30952 | D7: =10*Assumptions!B17+120*Assumptions!B18+Assumptions!B13 -> 12.30952
A8: Monthly team cost (€) | B8: =B7*10 -> 123.0952 | C8: =C7*25 -> 307.738 | D8: =D7*50 -> 615.476
A9: Monthly team margin (€) | B9: =B6-B8 -> 419.7048 | C9: =C6-C8 -> 946.012 | D9: =D6-D8 -> 1803.524
A10: Margin per user (%) | B10: =(B5-B7)/B5 -> 0.77322181 | C10: =(C5-C7)/C5 -> 0.75454596 | D10: =(D5-D7)/D5 -> 0.74556594
A11: Annual team revenue (€) | B11: =B6*12 -> 6513.6 | C11: =C6*12 -> 15045 | D11: =D6*12 -> 29028
A12: Annual team margin (€) | B12: =B9*12 -> 5036.4576 | C12: =C9*12 -> 11352.144 | D12: =D9*12 -> 21642.288
A15: Team Revenue Scenarios — Business Plan
A17: Metric | B17: 5 users (5% disc) | C17: 10 users (8% disc) | D17: 25 users (15% disc)
A18: Price per user (€/mo) | B18: =109*(1-0.05) -> 103.55 | C18: =109*(1-0.08) -> 100.28 | D18: =109*(1-0.15) -> 92.65
A19: Monthly team revenue (€) | B19: =B18*5 -> 517.75 | C19: =C18*10 -> 1002.8 | D19: =D18*25 -> 2316.25
A20: Cost per user (€/mo) | B20: =20*Assumptions!B17+240*Assumptions!B18+Assumptions!B13 -> 22.61904 | C20: =20*Assumptions!B17+240*Assumptions!B18+Assumptions!B13 -> 22.61904 | D20: =20*Assumptions!B17+240*Assumptions!B18+Assumptions!B13 -> 22.61904
A21: Monthly team cost (€) | B21: =B20*5 -> 113.0952 | C21: =C20*10 -> 226.1904 | D21: =D20*25 -> 565.476
A22: Monthly team margin (€) | B22: =B19-B21 -> 404.6548 | C22: =C19-C21 -> 776.6096 | D22: =D19-D21 -> 1750.774
A23: Margin per user (%) | B23: =(B18-B20)/B18 -> 0.78156408 | C23: =(C18-C20)/C18 -> 0.77444116 | D23: =(D18-D20)/D18 -> 0.75586573
A24: Annual team revenue (€) | B24: =B19*12 -> 6213 | C24: =C19*12 -> 12033.6 | D24: =D19*12 -> 27795
A25: Annual team margin (€) | B25: =B22*12 -> 4855.8576 | C25: =C22*12 -> 9319.3152 | D25: =D22*12 -> 21009.288
